{"text": "So you work on the side in a supermarket in addition to your studies?", "audio_path": "dataset_phrases/audio/work_long_female_en-US-Wavenet-H.wav", "gender": "female", "words": ["So", "you", "work", "on", "the", "side", "in", "a", "supermarket", "addition", "to", "your", "studies?"], "starts": [0.009999999776482582, 0.15558333694934845, 0.30533334612846375, 0.5383332967758179, 0.6594166159629822, 0.7122499346733093, 1.0664582252502441, 1.151999831199646, 1.2019997835159302, 1.951624870300293, 2.339707851409912, 2.421666145324707, 2.540499687194824], "size": "long", "tts": "en-US-Wavenet-H", "name": "work_long_female_en-US-Wavenet-H"}